compasscli/__init__.py
compasscli/compass.py
compasscli-0.1.3.dist-info/entry_points.txt
compasscli-0.1.3.dist-info/WHEEL
compasscli-0.1.3.dist-info/METADATA
compasscli-0.1.3.dist-info/RECORD
